{"info":{"_postman_id":"4bdf746b-9314-4917-abb1-24695fc3995b","name":"Accreditation","schema":"https://schema.getpostman.com/json/collection/v2.1.0/collection.json"},"item":[{"name":"list accreditations","id":"9d40bbed-ecee-4eab-821f-5799f7bbd16d","protocolProfileBehavior":{"disableBodyPruning":true},"request":{"method":"GET","header":[],"url":{"raw":"localhost:3000/accreditation/list","host":["localhost"],"port":"3000","path":["accreditation","list"]}},"response":[]},{"name":"add accreditation","id":"41cb2d4d-313f-455c-9240-b8c0ee4ec43d","protocolProfileBehavior":{"disableBodyPruning":true},"request":{"method":"POST","header":[],"url":{"raw":"localhost:3000/accreditation/add","host":["localhost"],"port":"3000","path":["accreditation","add"]}},"response":[]},{"name":"delete accreditation","id":"3dcf3c29-26f8-4042-8831-54f15c22b2a5","protocolProfileBehavior":{"disableBodyPruning":true},"request":{"method":"DELETE","header":[],"url":{"raw":"localhost:3000/accreditation/delete/:{id}","host":["localhost"],"port":"3000","path":["accreditation","delete",":{id}"],"variable":[{"key":"{id}","value":"","description":"Accreditation Id"}]}},"response":[]},{"name":"update accreditation","id":"6e30a369-5484-4cf7-8b40-80521d25d5d2","protocolProfileBehavior":{"disableBodyPruning":true},"request":{"method":"POST","header":[],"url":{"raw":"localhost:3000/accreditation/update/:{id}","host":["localhost"],"port":"3000","path":["accreditation","update",":{id}"],"variable":[{"id":"1763632d-675c-4fdc-bd9e-e4215371882b","key":"{id}","value":"","description":"Accreditation Id"}]}},"response":[]}]}