{"info":{"_postman_id":"5732c019-3ee0-4a71-81ee-06ad720c6139","name":"Course","schema":"https://schema.getpostman.com/json/collection/v2.1.0/collection.json"},"item":[{"name":"list courses","id":"b5a6e425-351b-45b5-a952-4c8c9e1f6d59","protocolProfileBehavior":{"disableBodyPruning":true},"request":{"method":"GET","header":[],"url":{"raw":"localhost:3000/course/list","host":["localhost"],"port":"3000","path":["course","list"]}},"response":[]},{"name":"create course","id":"7170b072-3fd3-4638-8d96-a9bfd8dc5db5","protocolProfileBehavior":{"disableBodyPruning":true},"request":{"method":"POST","header":[],"url":{"raw":"localhost:3000/course/create","host":["localhost"],"port":"3000","path":["course","create"]}},"response":[]},{"name":"delete course","id":"b0f066cf-fbcf-4b84-a5b6-00ae85208375","protocolProfileBehavior":{"disableBodyPruning":true},"request":{"method":"DELETE","header":[],"url":{"raw":"localhost:3000/course/delete/:{id}","host":["localhost"],"port":"3000","path":["course","delete",":{id}"],"variable":[{"key":"{id}","value":"","description":"Course Id"}]}},"response":[]},{"name":"update course","id":"c1526da0-51e4-4603-894f-9bd4755f7b84","protocolProfileBehavior":{"disableBodyPruning":true},"request":{"method":"POST","header":[],"url":{"raw":"localhost:3000/course/update/:{id}","host":["localhost"],"port":"3000","path":["course","update",":{id}"],"variable":[{"key":"{id}","value":"","description":"Course Id"}]}},"response":[]}]}