{"info":{"_postman_id":"d528bf3a-eb58-48ec-8a1c-c79c62d673e2","name":"Task Manager","schema":"https://schema.getpostman.com/json/collection/v2.1.0/collection.json"},"item":[{"name":"Get all tasks","id":"498dd549-7945-43a5-93ae-7413cf8508a6","protocolProfileBehavior":{"disableBodyPruning":true},"request":{"method":"GET","header":[],"body":{"mode":"raw","raw":"{\n    \"name\": \"testing tasks\"\n}","options":{"raw":{"language":"json"}}},"url":{"raw":"{{URL}}/tasks","host":["{{URL}}"],"path":["tasks"]}},"response":[]},{"name":"Create task","id":"fac4f81a-89d5-47c2-82c4-8696ee51b939","protocolProfileBehavior":{"disableBodyPruning":true},"request":{"auth":{"type":"bearer","bearer":[{"key":"token","value":"{{accessToken}}","type":"string"}]},"method":"POST","header":[],"body":{"mode":"raw","raw":"{\n    \"name\": \"bleh\",\n    \"completed\": true\n}","options":{"raw":{"language":"json"}}},"url":{"raw":"{{URL}}/tasks","host":["{{URL}}"],"path":["tasks"]}},"response":[]},{"name":"Get single task","id":"9a0585c1-913d-42da-a141-68717d8260aa","protocolProfileBehavior":{"disableBodyPruning":true},"request":{"method":"GET","header":[],"body":{"mode":"raw","raw":"{\n    \"id\": \"64fc334901f0be01bc4d73bc\"\n}","options":{"raw":{"language":"json"}}},"url":{"raw":"{{URL}}/tasks/64fc336001f0be01bc4d73c0","host":["{{URL}}"],"path":["tasks","64fc336001f0be01bc4d73c0"]}},"response":[]},{"name":"Delete task","id":"d3cb2ee4-f6af-456d-a2ba-bb4a5d45e75f","protocolProfileBehavior":{"disableBodyPruning":true},"request":{"method":"DELETE","header":[],"body":{"mode":"raw","raw":"{\n    \"name\": \"bleh\"\n}","options":{"raw":{"language":"json"}}},"url":{"raw":"{{URL}}/tasks/hello","host":["{{URL}}"],"path":["tasks","hello"]}},"response":[]},{"name":"Update task","id":"80dc1e33-3faa-4ca7-b7c3-acd1d3e1a471","protocolProfileBehavior":{"disableBodyPruning":true},"request":{"method":"PATCH","header":[],"body":{"mode":"raw","raw":"{\n    \"name\": \"bleh\"\n}","options":{"raw":{"language":"json"}}},"url":{"raw":"{{URL}}/tasks/123","host":["{{URL}}"],"path":["tasks","123"]}},"response":[]}]}